{
  "metadata": {
    "haloVersion": "2.21.10",
    "javaVersion": "21.0.9",
    "themeVersion": "v1.15.0",
    "lhciVersion": "0.15.1",
    "generatedAt": "2025-11-22T11:49:23.411Z"
  },
  "timestamp": "2025-11-22T11:49:23.411Z",
  "results": [
    {
      "url": "/",
      "resources": {
        "document": {
          "transferSize": 2870,
          "resourceSize": 6689
        },
        "font": {
          "transferSize": 0,
          "resourceSize": 0
        },
        "script": {
          "transferSize": 331610,
          "resourceSize": 1048047
        },
        "stylesheet": {
          "transferSize": 319788,
          "resourceSize": 712979
        },
        "image": {
          "transferSize": 224175,
          "resourceSize": 224006
        },
        "fetch": {
          "transferSize": 771,
          "resourceSize": 195
        },
        "other": {
          "transferSize": 1043,
          "resourceSize": 216
        },
        "total": {
          "transferSize": 880257,
          "resourceSize": 1992132
        }
      },
      "themeResources": {
        "document": {
          "transferSize": 0,
          "resourceSize": 0
        },
        "font": {
          "transferSize": 0,
          "resourceSize": 0
        },
        "script": {
          "transferSize": 147947,
          "resourceSize": 433190
        },
        "stylesheet": {
          "transferSize": 317166,
          "resourceSize": 710689
        },
        "image": {
          "transferSize": 224175,
          "resourceSize": 224006
        },
        "fetch": {
          "transferSize": 0,
          "resourceSize": 0
        },
        "other": {
          "transferSize": 425,
          "resourceSize": 0
        },
        "total": {
          "transferSize": 689713,
          "resourceSize": 1367885
        }
      }
    },
    {
      "url": "/archives",
      "resources": {
        "document": {
          "transferSize": 2842,
          "resourceSize": 6718
        },
        "font": {
          "transferSize": 0,
          "resourceSize": 0
        },
        "script": {
          "transferSize": 331610,
          "resourceSize": 1048047
        },
        "stylesheet": {
          "transferSize": 319788,
          "resourceSize": 712979
        },
        "image": {
          "transferSize": 224175,
          "resourceSize": 224006
        },
        "fetch": {
          "transferSize": 773,
          "resourceSize": 195
        },
        "other": {
          "transferSize": 1043,
          "resourceSize": 216
        },
        "total": {
          "transferSize": 880231,
          "resourceSize": 1992161
        }
      },
      "themeResources": {
        "document": {
          "transferSize": 0,
          "resourceSize": 0
        },
        "font": {
          "transferSize": 0,
          "resourceSize": 0
        },
        "script": {
          "transferSize": 147947,
          "resourceSize": 433190
        },
        "stylesheet": {
          "transferSize": 317166,
          "resourceSize": 710689
        },
        "image": {
          "transferSize": 224175,
          "resourceSize": 224006
        },
        "fetch": {
          "transferSize": 0,
          "resourceSize": 0
        },
        "other": {
          "transferSize": 425,
          "resourceSize": 0
        },
        "total": {
          "transferSize": 689713,
          "resourceSize": 1367885
        }
      }
    },
    {
      "url": "/archives/hello-halo",
      "resources": {
        "document": {
          "transferSize": 5895,
          "resourceSize": 19532
        },
        "font": {
          "transferSize": 0,
          "resourceSize": 0
        },
        "script": {
          "transferSize": 733323,
          "resourceSize": 2205074
        },
        "stylesheet": {
          "transferSize": 319788,
          "resourceSize": 712979
        },
        "image": {
          "transferSize": 0,
          "resourceSize": 0
        },
        "fetch": {
          "transferSize": 7809,
          "resourceSize": 6933
        },
        "other": {
          "transferSize": 618,
          "resourceSize": 216
        },
        "total": {
          "transferSize": 1067433,
          "resourceSize": 2944734
        }
      },
      "themeResources": {
        "document": {
          "transferSize": 0,
          "resourceSize": 0
        },
        "font": {
          "transferSize": 0,
          "resourceSize": 0
        },
        "script": {
          "transferSize": 151733,
          "resourceSize": 442350
        },
        "stylesheet": {
          "transferSize": 317166,
          "resourceSize": 710689
        },
        "image": {
          "transferSize": 0,
          "resourceSize": 0
        },
        "fetch": {
          "transferSize": 0,
          "resourceSize": 0
        },
        "other": {
          "transferSize": 0,
          "resourceSize": 0
        },
        "total": {
          "transferSize": 468899,
          "resourceSize": 1153039
        }
      }
    },
    {
      "url": "/tags",
      "resources": {
        "document": {
          "transferSize": 2699,
          "resourceSize": 6176
        },
        "font": {
          "transferSize": 0,
          "resourceSize": 0
        },
        "script": {
          "transferSize": 331610,
          "resourceSize": 1048047
        },
        "stylesheet": {
          "transferSize": 319788,
          "resourceSize": 712979
        },
        "image": {
          "transferSize": 224175,
          "resourceSize": 224006
        },
        "fetch": {
          "transferSize": 772,
          "resourceSize": 195
        },
        "other": {
          "transferSize": 1043,
          "resourceSize": 216
        },
        "total": {
          "transferSize": 880087,
          "resourceSize": 1991619
        }
      },
      "themeResources": {
        "document": {
          "transferSize": 0,
          "resourceSize": 0
        },
        "font": {
          "transferSize": 0,
          "resourceSize": 0
        },
        "script": {
          "transferSize": 147947,
          "resourceSize": 433190
        },
        "stylesheet": {
          "transferSize": 317166,
          "resourceSize": 710689
        },
        "image": {
          "transferSize": 224175,
          "resourceSize": 224006
        },
        "fetch": {
          "transferSize": 0,
          "resourceSize": 0
        },
        "other": {
          "transferSize": 425,
          "resourceSize": 0
        },
        "total": {
          "transferSize": 689713,
          "resourceSize": 1367885
        }
      }
    },
    {
      "url": "/tags/halo",
      "resources": {
        "document": {
          "transferSize": 2833,
          "resourceSize": 6528
        },
        "font": {
          "transferSize": 0,
          "resourceSize": 0
        },
        "script": {
          "transferSize": 331610,
          "resourceSize": 1048047
        },
        "stylesheet": {
          "transferSize": 319788,
          "resourceSize": 712979
        },
        "image": {
          "transferSize": 224175,
          "resourceSize": 224006
        },
        "fetch": {
          "transferSize": 772,
          "resourceSize": 195
        },
        "other": {
          "transferSize": 1044,
          "resourceSize": 217
        },
        "total": {
          "transferSize": 880222,
          "resourceSize": 1991972
        }
      },
      "themeResources": {
        "document": {
          "transferSize": 0,
          "resourceSize": 0
        },
        "font": {
          "transferSize": 0,
          "resourceSize": 0
        },
        "script": {
          "transferSize": 147947,
          "resourceSize": 433190
        },
        "stylesheet": {
          "transferSize": 317166,
          "resourceSize": 710689
        },
        "image": {
          "transferSize": 224175,
          "resourceSize": 224006
        },
        "fetch": {
          "transferSize": 0,
          "resourceSize": 0
        },
        "other": {
          "transferSize": 425,
          "resourceSize": 0
        },
        "total": {
          "transferSize": 689713,
          "resourceSize": 1367885
        }
      }
    },
    {
      "url": "/categories",
      "resources": {
        "document": {
          "transferSize": 2708,
          "resourceSize": 6158
        },
        "font": {
          "transferSize": 0,
          "resourceSize": 0
        },
        "script": {
          "transferSize": 331610,
          "resourceSize": 1048047
        },
        "stylesheet": {
          "transferSize": 319788,
          "resourceSize": 712979
        },
        "image": {
          "transferSize": 224175,
          "resourceSize": 224006
        },
        "fetch": {
          "transferSize": 767,
          "resourceSize": 195
        },
        "other": {
          "transferSize": 1044,
          "resourceSize": 217
        },
        "total": {
          "transferSize": 880092,
          "resourceSize": 1991602
        }
      },
      "themeResources": {
        "document": {
          "transferSize": 0,
          "resourceSize": 0
        },
        "font": {
          "transferSize": 0,
          "resourceSize": 0
        },
        "script": {
          "transferSize": 147947,
          "resourceSize": 433190
        },
        "stylesheet": {
          "transferSize": 317166,
          "resourceSize": 710689
        },
        "image": {
          "transferSize": 224175,
          "resourceSize": 224006
        },
        "fetch": {
          "transferSize": 0,
          "resourceSize": 0
        },
        "other": {
          "transferSize": 425,
          "resourceSize": 0
        },
        "total": {
          "transferSize": 689713,
          "resourceSize": 1367885
        }
      }
    },
    {
      "url": "/categories/default",
      "resources": {
        "document": {
          "transferSize": 2887,
          "resourceSize": 6638
        },
        "font": {
          "transferSize": 0,
          "resourceSize": 0
        },
        "script": {
          "transferSize": 331610,
          "resourceSize": 1048047
        },
        "stylesheet": {
          "transferSize": 319788,
          "resourceSize": 712979
        },
        "image": {
          "transferSize": 224175,
          "resourceSize": 224006
        },
        "fetch": {
          "transferSize": 770,
          "resourceSize": 195
        },
        "other": {
          "transferSize": 1044,
          "resourceSize": 217
        },
        "total": {
          "transferSize": 880274,
          "resourceSize": 1992082
        }
      },
      "themeResources": {
        "document": {
          "transferSize": 0,
          "resourceSize": 0
        },
        "font": {
          "transferSize": 0,
          "resourceSize": 0
        },
        "script": {
          "transferSize": 147947,
          "resourceSize": 433190
        },
        "stylesheet": {
          "transferSize": 317166,
          "resourceSize": 710689
        },
        "image": {
          "transferSize": 224175,
          "resourceSize": 224006
        },
        "fetch": {
          "transferSize": 0,
          "resourceSize": 0
        },
        "other": {
          "transferSize": 425,
          "resourceSize": 0
        },
        "total": {
          "transferSize": 689713,
          "resourceSize": 1367885
        }
      }
    },
    {
      "url": "/authors/admin",
      "resources": {
        "document": {
          "transferSize": 3542,
          "resourceSize": 8954
        },
        "font": {
          "transferSize": 0,
          "resourceSize": 0
        },
        "script": {
          "transferSize": 331610,
          "resourceSize": 1048047
        },
        "stylesheet": {
          "transferSize": 319788,
          "resourceSize": 712979
        },
        "image": {
          "transferSize": 224175,
          "resourceSize": 448012
        },
        "fetch": {
          "transferSize": 763,
          "resourceSize": 195
        },
        "other": {
          "transferSize": 1044,
          "resourceSize": 217
        },
        "total": {
          "transferSize": 880922,
          "resourceSize": 2218404
        }
      },
      "themeResources": {
        "document": {
          "transferSize": 0,
          "resourceSize": 0
        },
        "font": {
          "transferSize": 0,
          "resourceSize": 0
        },
        "script": {
          "transferSize": 147947,
          "resourceSize": 433190
        },
        "stylesheet": {
          "transferSize": 317166,
          "resourceSize": 710689
        },
        "image": {
          "transferSize": 224175,
          "resourceSize": 448012
        },
        "fetch": {
          "transferSize": 0,
          "resourceSize": 0
        },
        "other": {
          "transferSize": 425,
          "resourceSize": 0
        },
        "total": {
          "transferSize": 689713,
          "resourceSize": 1591891
        }
      }
    },
    {
      "url": "/about",
      "resources": {
        "document": {
          "transferSize": 3698,
          "resourceSize": 8581
        },
        "font": {
          "transferSize": 0,
          "resourceSize": 0
        },
        "script": {
          "transferSize": 733323,
          "resourceSize": 2205074
        },
        "stylesheet": {
          "transferSize": 319788,
          "resourceSize": 712979
        },
        "image": {
          "transferSize": 224175,
          "resourceSize": 224006
        },
        "fetch": {
          "transferSize": 3941,
          "resourceSize": 1443
        },
        "other": {
          "transferSize": 1044,
          "resourceSize": 217
        },
        "total": {
          "transferSize": 1285969,
          "resourceSize": 3152300
        }
      },
      "themeResources": {
        "document": {
          "transferSize": 0,
          "resourceSize": 0
        },
        "font": {
          "transferSize": 0,
          "resourceSize": 0
        },
        "script": {
          "transferSize": 151733,
          "resourceSize": 442350
        },
        "stylesheet": {
          "transferSize": 317166,
          "resourceSize": 710689
        },
        "image": {
          "transferSize": 224175,
          "resourceSize": 224006
        },
        "fetch": {
          "transferSize": 0,
          "resourceSize": 0
        },
        "other": {
          "transferSize": 425,
          "resourceSize": 0
        },
        "total": {
          "transferSize": 693499,
          "resourceSize": 1377045
        }
      }
    }
  ]
}