{
  "metadata": {
    "haloVersion": "2.22.1",
    "javaVersion": "21.0.9",
    "themeVersion": "v1.29.1",
    "lhciVersion": "0.15.1",
    "generatedAt": "2025-12-25T01:00:13.331Z"
  },
  "timestamp": "2025-12-25T01:00:13.331Z",
  "results": [
    {
      "url": "/",
      "resources": {
        "document": {
          "transferSize": 2145,
          "resourceSize": 5633
        },
        "font": {
          "transferSize": 0,
          "resourceSize": 0
        },
        "script": {
          "transferSize": 145486,
          "resourceSize": 402557
        },
        "stylesheet": {
          "transferSize": 317298,
          "resourceSize": 716003
        },
        "image": {
          "transferSize": 224175,
          "resourceSize": 224006
        },
        "fetch": {
          "transferSize": 764,
          "resourceSize": 195
        },
        "other": {
          "transferSize": 362,
          "resourceSize": 275
        },
        "total": {
          "transferSize": 690230,
          "resourceSize": 1348669
        }
      },
      "themeResources": {
        "document": {
          "transferSize": 0,
          "resourceSize": 0
        },
        "font": {
          "transferSize": 0,
          "resourceSize": 0
        },
        "script": {
          "transferSize": 145486,
          "resourceSize": 402557
        },
        "stylesheet": {
          "transferSize": 317298,
          "resourceSize": 716003
        },
        "image": {
          "transferSize": 224175,
          "resourceSize": 224006
        },
        "fetch": {
          "transferSize": 0,
          "resourceSize": 0
        },
        "other": {
          "transferSize": 362,
          "resourceSize": 275
        },
        "total": {
          "transferSize": 687321,
          "resourceSize": 1342841
        }
      }
    },
    {
      "url": "/archives",
      "resources": {
        "document": {
          "transferSize": 2109,
          "resourceSize": 5622
        },
        "font": {
          "transferSize": 0,
          "resourceSize": 0
        },
        "script": {
          "transferSize": 145486,
          "resourceSize": 402557
        },
        "stylesheet": {
          "transferSize": 317298,
          "resourceSize": 716003
        },
        "image": {
          "transferSize": 224175,
          "resourceSize": 224006
        },
        "fetch": {
          "transferSize": 767,
          "resourceSize": 195
        },
        "other": {
          "transferSize": 362,
          "resourceSize": 275
        },
        "total": {
          "transferSize": 690197,
          "resourceSize": 1348658
        }
      },
      "themeResources": {
        "document": {
          "transferSize": 0,
          "resourceSize": 0
        },
        "font": {
          "transferSize": 0,
          "resourceSize": 0
        },
        "script": {
          "transferSize": 145486,
          "resourceSize": 402557
        },
        "stylesheet": {
          "transferSize": 317298,
          "resourceSize": 716003
        },
        "image": {
          "transferSize": 224175,
          "resourceSize": 224006
        },
        "fetch": {
          "transferSize": 0,
          "resourceSize": 0
        },
        "other": {
          "transferSize": 362,
          "resourceSize": 275
        },
        "total": {
          "transferSize": 687321,
          "resourceSize": 1342841
        }
      }
    },
    {
      "url": "/archives/hello-halo",
      "resources": {
        "document": {
          "transferSize": 5708,
          "resourceSize": 24067
        },
        "font": {
          "transferSize": 0,
          "resourceSize": 0
        },
        "script": {
          "transferSize": 151283,
          "resourceSize": 413555
        },
        "stylesheet": {
          "transferSize": 317298,
          "resourceSize": 716003
        },
        "image": {
          "transferSize": 0,
          "resourceSize": 0
        },
        "fetch": {
          "transferSize": 9099,
          "resourceSize": 11929
        },
        "other": {
          "transferSize": 362,
          "resourceSize": 275
        },
        "total": {
          "transferSize": 483750,
          "resourceSize": 1165829
        }
      },
      "themeResources": {
        "document": {
          "transferSize": 0,
          "resourceSize": 0
        },
        "font": {
          "transferSize": 0,
          "resourceSize": 0
        },
        "script": {
          "transferSize": 149272,
          "resourceSize": 411717
        },
        "stylesheet": {
          "transferSize": 317298,
          "resourceSize": 716003
        },
        "image": {
          "transferSize": 0,
          "resourceSize": 0
        },
        "fetch": {
          "transferSize": 0,
          "resourceSize": 0
        },
        "other": {
          "transferSize": 362,
          "resourceSize": 275
        },
        "total": {
          "transferSize": 466932,
          "resourceSize": 1127995
        }
      }
    },
    {
      "url": "/tags",
      "resources": {
        "document": {
          "transferSize": 1980,
          "resourceSize": 5061
        },
        "font": {
          "transferSize": 0,
          "resourceSize": 0
        },
        "script": {
          "transferSize": 145486,
          "resourceSize": 402557
        },
        "stylesheet": {
          "transferSize": 317298,
          "resourceSize": 716003
        },
        "image": {
          "transferSize": 224175,
          "resourceSize": 224006
        },
        "fetch": {
          "transferSize": 770,
          "resourceSize": 195
        },
        "other": {
          "transferSize": 362,
          "resourceSize": 275
        },
        "total": {
          "transferSize": 690071,
          "resourceSize": 1348097
        }
      },
      "themeResources": {
        "document": {
          "transferSize": 0,
          "resourceSize": 0
        },
        "font": {
          "transferSize": 0,
          "resourceSize": 0
        },
        "script": {
          "transferSize": 145486,
          "resourceSize": 402557
        },
        "stylesheet": {
          "transferSize": 317298,
          "resourceSize": 716003
        },
        "image": {
          "transferSize": 224175,
          "resourceSize": 224006
        },
        "fetch": {
          "transferSize": 0,
          "resourceSize": 0
        },
        "other": {
          "transferSize": 362,
          "resourceSize": 275
        },
        "total": {
          "transferSize": 687321,
          "resourceSize": 1342841
        }
      }
    },
    {
      "url": "/tags/halo",
      "resources": {
        "document": {
          "transferSize": 2112,
          "resourceSize": 5454
        },
        "font": {
          "transferSize": 0,
          "resourceSize": 0
        },
        "script": {
          "transferSize": 145486,
          "resourceSize": 402557
        },
        "stylesheet": {
          "transferSize": 317298,
          "resourceSize": 716003
        },
        "image": {
          "transferSize": 224175,
          "resourceSize": 224006
        },
        "fetch": {
          "transferSize": 770,
          "resourceSize": 195
        },
        "other": {
          "transferSize": 362,
          "resourceSize": 275
        },
        "total": {
          "transferSize": 690203,
          "resourceSize": 1348490
        }
      },
      "themeResources": {
        "document": {
          "transferSize": 0,
          "resourceSize": 0
        },
        "font": {
          "transferSize": 0,
          "resourceSize": 0
        },
        "script": {
          "transferSize": 145486,
          "resourceSize": 402557
        },
        "stylesheet": {
          "transferSize": 317298,
          "resourceSize": 716003
        },
        "image": {
          "transferSize": 224175,
          "resourceSize": 224006
        },
        "fetch": {
          "transferSize": 0,
          "resourceSize": 0
        },
        "other": {
          "transferSize": 362,
          "resourceSize": 275
        },
        "total": {
          "transferSize": 687321,
          "resourceSize": 1342841
        }
      }
    },
    {
      "url": "/categories",
      "resources": {
        "document": {
          "transferSize": 1993,
          "resourceSize": 5043
        },
        "font": {
          "transferSize": 0,
          "resourceSize": 0
        },
        "script": {
          "transferSize": 145486,
          "resourceSize": 402557
        },
        "stylesheet": {
          "transferSize": 317298,
          "resourceSize": 716003
        },
        "image": {
          "transferSize": 224175,
          "resourceSize": 224006
        },
        "fetch": {
          "transferSize": 770,
          "resourceSize": 195
        },
        "other": {
          "transferSize": 362,
          "resourceSize": 275
        },
        "total": {
          "transferSize": 690084,
          "resourceSize": 1348079
        }
      },
      "themeResources": {
        "document": {
          "transferSize": 0,
          "resourceSize": 0
        },
        "font": {
          "transferSize": 0,
          "resourceSize": 0
        },
        "script": {
          "transferSize": 145486,
          "resourceSize": 402557
        },
        "stylesheet": {
          "transferSize": 317298,
          "resourceSize": 716003
        },
        "image": {
          "transferSize": 224175,
          "resourceSize": 224006
        },
        "fetch": {
          "transferSize": 0,
          "resourceSize": 0
        },
        "other": {
          "transferSize": 362,
          "resourceSize": 275
        },
        "total": {
          "transferSize": 687321,
          "resourceSize": 1342841
        }
      }
    },
    {
      "url": "/categories/default",
      "resources": {
        "document": {
          "transferSize": 2187,
          "resourceSize": 5564
        },
        "font": {
          "transferSize": 0,
          "resourceSize": 0
        },
        "script": {
          "transferSize": 145486,
          "resourceSize": 402557
        },
        "stylesheet": {
          "transferSize": 317298,
          "resourceSize": 716003
        },
        "image": {
          "transferSize": 224175,
          "resourceSize": 224006
        },
        "fetch": {
          "transferSize": 764,
          "resourceSize": 195
        },
        "other": {
          "transferSize": 362,
          "resourceSize": 275
        },
        "total": {
          "transferSize": 690272,
          "resourceSize": 1348600
        }
      },
      "themeResources": {
        "document": {
          "transferSize": 0,
          "resourceSize": 0
        },
        "font": {
          "transferSize": 0,
          "resourceSize": 0
        },
        "script": {
          "transferSize": 145486,
          "resourceSize": 402557
        },
        "stylesheet": {
          "transferSize": 317298,
          "resourceSize": 716003
        },
        "image": {
          "transferSize": 224175,
          "resourceSize": 224006
        },
        "fetch": {
          "transferSize": 0,
          "resourceSize": 0
        },
        "other": {
          "transferSize": 362,
          "resourceSize": 275
        },
        "total": {
          "transferSize": 687321,
          "resourceSize": 1342841
        }
      }
    },
    {
      "url": "/authors/admin",
      "resources": {
        "document": {
          "transferSize": 3031,
          "resourceSize": 9137
        },
        "font": {
          "transferSize": 0,
          "resourceSize": 0
        },
        "script": {
          "transferSize": 145486,
          "resourceSize": 402557
        },
        "stylesheet": {
          "transferSize": 317298,
          "resourceSize": 716003
        },
        "image": {
          "transferSize": 448350,
          "resourceSize": 448012
        },
        "fetch": {
          "transferSize": 1317,
          "resourceSize": 604
        },
        "other": {
          "transferSize": 362,
          "resourceSize": 275
        },
        "total": {
          "transferSize": 915844,
          "resourceSize": 1576588
        }
      },
      "themeResources": {
        "document": {
          "transferSize": 0,
          "resourceSize": 0
        },
        "font": {
          "transferSize": 0,
          "resourceSize": 0
        },
        "script": {
          "transferSize": 145486,
          "resourceSize": 402557
        },
        "stylesheet": {
          "transferSize": 317298,
          "resourceSize": 716003
        },
        "image": {
          "transferSize": 448350,
          "resourceSize": 448012
        },
        "fetch": {
          "transferSize": 0,
          "resourceSize": 0
        },
        "other": {
          "transferSize": 362,
          "resourceSize": 275
        },
        "total": {
          "transferSize": 911496,
          "resourceSize": 1566847
        }
      }
    },
    {
      "url": "/about",
      "resources": {
        "document": {
          "transferSize": 2867,
          "resourceSize": 6947
        },
        "font": {
          "transferSize": 0,
          "resourceSize": 0
        },
        "script": {
          "transferSize": 151283,
          "resourceSize": 413555
        },
        "stylesheet": {
          "transferSize": 317298,
          "resourceSize": 716003
        },
        "image": {
          "transferSize": 224175,
          "resourceSize": 224006
        },
        "fetch": {
          "transferSize": 1122,
          "resourceSize": 195
        },
        "other": {
          "transferSize": 363,
          "resourceSize": 276
        },
        "total": {
          "transferSize": 697108,
          "resourceSize": 1360982
        }
      },
      "themeResources": {
        "document": {
          "transferSize": 0,
          "resourceSize": 0
        },
        "font": {
          "transferSize": 0,
          "resourceSize": 0
        },
        "script": {
          "transferSize": 149272,
          "resourceSize": 411717
        },
        "stylesheet": {
          "transferSize": 317298,
          "resourceSize": 716003
        },
        "image": {
          "transferSize": 224175,
          "resourceSize": 224006
        },
        "fetch": {
          "transferSize": 0,
          "resourceSize": 0
        },
        "other": {
          "transferSize": 363,
          "resourceSize": 276
        },
        "total": {
          "transferSize": 691108,
          "resourceSize": 1352002
        }
      }
    }
  ]
}