{
  "metadata": {
    "haloVersion": null,
    "javaVersion": null,
    "themeVersion": "v1.41.0",
    "lhciVersion": null,
    "generatedAt": "2025-11-21T06:53:28.821Z"
  },
  "timestamp": "2025-11-21T06:53:28.821Z",
  "results": [
    {
      "url": "http://localhost:8090/",
      "resources": {
        "document": {
          "transferSize": 2377,
          "resourceSize": 6404
        },
        "font": {
          "transferSize": 0,
          "resourceSize": 0
        },
        "script": {
          "transferSize": 295811,
          "resourceSize": 933797
        },
        "stylesheet": {
          "transferSize": 319862,
          "resourceSize": 733145
        },
        "image": {
          "transferSize": 224175,
          "resourceSize": 224006
        },
        "fetch": {
          "transferSize": 766,
          "resourceSize": 195
        },
        "other": {
          "transferSize": 618,
          "resourceSize": 216
        },
        "total": {
          "transferSize": 843609,
          "resourceSize": 1897763
        }
      }
    },
    {
      "url": "http://localhost:8090/archives",
      "resources": {
        "document": {
          "transferSize": 2348,
          "resourceSize": 6416
        },
        "font": {
          "transferSize": 0,
          "resourceSize": 0
        },
        "script": {
          "transferSize": 295811,
          "resourceSize": 933797
        },
        "stylesheet": {
          "transferSize": 319862,
          "resourceSize": 733145
        },
        "image": {
          "transferSize": 224175,
          "resourceSize": 224006
        },
        "fetch": {
          "transferSize": 769,
          "resourceSize": 195
        },
        "other": {
          "transferSize": 618,
          "resourceSize": 216
        },
        "total": {
          "transferSize": 843583,
          "resourceSize": 1897775
        }
      }
    },
    {
      "url": "http://localhost:8090/archives/hello-halo",
      "resources": {
        "document": {
          "transferSize": 5552,
          "resourceSize": 25011
        },
        "font": {
          "transferSize": 0,
          "resourceSize": 0
        },
        "script": {
          "transferSize": 693738,
          "resourceSize": 2081664
        },
        "stylesheet": {
          "transferSize": 319862,
          "resourceSize": 733145
        },
        "image": {
          "transferSize": 0,
          "resourceSize": 0
        },
        "fetch": {
          "transferSize": 12308,
          "resourceSize": 13177
        },
        "other": {
          "transferSize": 618,
          "resourceSize": 216
        },
        "total": {
          "transferSize": 1032078,
          "resourceSize": 2853213
        }
      }
    },
    {
      "url": "http://localhost:8090/tags",
      "resources": {
        "document": {
          "transferSize": 2226,
          "resourceSize": 5910
        },
        "font": {
          "transferSize": 0,
          "resourceSize": 0
        },
        "script": {
          "transferSize": 295811,
          "resourceSize": 933797
        },
        "stylesheet": {
          "transferSize": 319862,
          "resourceSize": 733145
        },
        "image": {
          "transferSize": 224175,
          "resourceSize": 224006
        },
        "fetch": {
          "transferSize": 770,
          "resourceSize": 195
        },
        "other": {
          "transferSize": 618,
          "resourceSize": 216
        },
        "total": {
          "transferSize": 843462,
          "resourceSize": 1897269
        }
      }
    },
    {
      "url": "http://localhost:8090/tags/halo",
      "resources": {
        "document": {
          "transferSize": 2358,
          "resourceSize": 6286
        },
        "font": {
          "transferSize": 0,
          "resourceSize": 0
        },
        "script": {
          "transferSize": 295811,
          "resourceSize": 933797
        },
        "stylesheet": {
          "transferSize": 319862,
          "resourceSize": 733145
        },
        "image": {
          "transferSize": 224175,
          "resourceSize": 224006
        },
        "fetch": {
          "transferSize": 768,
          "resourceSize": 195
        },
        "other": {
          "transferSize": 618,
          "resourceSize": 216
        },
        "total": {
          "transferSize": 843592,
          "resourceSize": 1897645
        }
      }
    },
    {
      "url": "http://localhost:8090/categories",
      "resources": {
        "document": {
          "transferSize": 2227,
          "resourceSize": 5837
        },
        "font": {
          "transferSize": 0,
          "resourceSize": 0
        },
        "script": {
          "transferSize": 295811,
          "resourceSize": 933797
        },
        "stylesheet": {
          "transferSize": 319862,
          "resourceSize": 733145
        },
        "image": {
          "transferSize": 224175,
          "resourceSize": 224006
        },
        "fetch": {
          "transferSize": 768,
          "resourceSize": 195
        },
        "other": {
          "transferSize": 618,
          "resourceSize": 216
        },
        "total": {
          "transferSize": 843461,
          "resourceSize": 1897196
        }
      }
    },
    {
      "url": "http://localhost:8090/categories/default",
      "resources": {
        "document": {
          "transferSize": 2429,
          "resourceSize": 6396
        },
        "font": {
          "transferSize": 0,
          "resourceSize": 0
        },
        "script": {
          "transferSize": 295811,
          "resourceSize": 933797
        },
        "stylesheet": {
          "transferSize": 319862,
          "resourceSize": 733145
        },
        "image": {
          "transferSize": 224175,
          "resourceSize": 224006
        },
        "fetch": {
          "transferSize": 767,
          "resourceSize": 195
        },
        "other": {
          "transferSize": 619,
          "resourceSize": 217
        },
        "total": {
          "transferSize": 843663,
          "resourceSize": 1897756
        }
      }
    },
    {
      "url": "http://localhost:8090/authors/admin",
      "resources": {
        "document": {
          "transferSize": 3385,
          "resourceSize": 10352
        },
        "font": {
          "transferSize": 0,
          "resourceSize": 0
        },
        "script": {
          "transferSize": 295811,
          "resourceSize": 933797
        },
        "stylesheet": {
          "transferSize": 319862,
          "resourceSize": 733145
        },
        "image": {
          "transferSize": 224175,
          "resourceSize": 224006
        },
        "fetch": {
          "transferSize": 1278,
          "resourceSize": 557
        },
        "other": {
          "transferSize": 619,
          "resourceSize": 217
        },
        "total": {
          "transferSize": 845130,
          "resourceSize": 1902074
        }
      }
    },
    {
      "url": "http://localhost:8090/about",
      "resources": {
        "document": {
          "transferSize": 2702,
          "resourceSize": 7137
        },
        "font": {
          "transferSize": 0,
          "resourceSize": 0
        },
        "script": {
          "transferSize": 693738,
          "resourceSize": 2081664
        },
        "stylesheet": {
          "transferSize": 319862,
          "resourceSize": 733145
        },
        "image": {
          "transferSize": 224175,
          "resourceSize": 224006
        },
        "fetch": {
          "transferSize": 3945,
          "resourceSize": 1443
        },
        "other": {
          "transferSize": 619,
          "resourceSize": 217
        },
        "total": {
          "transferSize": 1245041,
          "resourceSize": 3047612
        }
      }
    }
  ]
}